CHANGES.rst
LICENSE
MANIFEST.in
README.rst
setup.py
debug_toolbar_autoreload/__init__.py
debug_toolbar_autoreload/conf.py
debug_toolbar_autoreload/filesystem.py
debug_toolbar_autoreload/panels.py
debug_toolbar_autoreload/urls.py
debug_toolbar_autoreload/views.py
debug_toolbar_autoreload/templates/debug_toolbar/panels/autoreload.html
django_debug_toolbar_autoreload.egg-info/PKG-INFO
django_debug_toolbar_autoreload.egg-info/SOURCES.txt
django_debug_toolbar_autoreload.egg-info/dependency_links.txt
django_debug_toolbar_autoreload.egg-info/not-zip-safe
django_debug_toolbar_autoreload.egg-info/top_level.txt