Metadata-Version: 1.1
Name: django-debug-toolbar-autoreload
Version: 0.2.0
Summary: Automatically reloads your browser when a template, css or javascript file was modified.
Home-page: https://github.com/gregmuellegger/django-debug-toolbar-autoreload
Author: Gregor Müllegger
Author-email: gregor@muellegger.de
License: BSD licence, see LICENSE file
Platform: UNKNOWN
Classifier: Development Status :: 4 - Beta
Classifier: Environment :: Web Environment
Classifier: Framework :: Django
Classifier: Intended Audience :: Developers
Classifier: License :: OSI Approved :: BSD License
Classifier: Natural Language :: English
Classifier: Programming Language :: Python
